juyilib/__init__.py
juyilib/test.py
juyilib/utils/__init__.py
juyilib/utils/date_util.py
juyilib/utils/file_util.py
juyilib/utils/int_util.py
juyilib-0.8.0.dist-info/METADATA
juyilib-0.8.0.dist-info/RECORD
juyilib-0.8.0.dist-info/WHEEL
juyilib-0.8.0.dist-info/top_level.txt
juyilib-0.8.0.dist-info/zip-safe
