Metadata-Version: 2.1
Name: juyilib
Version: 0.8.0
Summary: A Python library for myself.
Home-page: http://bittool.pro
Author: Seakingii
Author-email: seakingii@gmail.com
License: MIT
Platform: UNKNOWN
Classifier: License :: OSI Approved :: MIT License
Classifier: Operating System :: OS Independent
Classifier: Programming Language :: Python :: 3
